tapedeck/__init__.py
tapedeck/config.py
tapedeck/search.py
tapedeck/cli/__init__.py
tapedeck/cli/main.py
tapedeck/cli/play.py
tapedeck/cli/search.py
tests/__init__.py
tests/conftest.py
tests/test_api.py
tests/test_cli.py
tests/test_cli_play.py
tests/test_cli_search.py
tests/test_config.py
tests/test_search.py
tapedeck-0.0.5.dist-info/LICENSE
tapedeck-0.0.5.dist-info/METADATA
tapedeck-0.0.5.dist-info/WHEEL
tapedeck-0.0.5.dist-info/entry_points.txt
tapedeck-0.0.5.dist-info/top_level.txt
tapedeck-0.0.5.dist-info/RECORD
