Metadata-Version: 2.1
Name: tapedeck
Version: 0.0.5
Summary: A music player
Home-page: http://github.com/zthompson47/tapedeck
Author: Zach Thompson
Author-email: zach@allotropic.com
License: MIT
Platform: UNKNOWN
Classifier: Programming Language :: Python :: 3.5
Classifier: License :: OSI Approved :: MIT License
Classifier: Operating System :: OS Independent
Requires-Dist: blessings (>=1.7)
Requires-Dist: reel (>=0.0.5)
Requires-Dist: trio (>=0.10.0)
